alexa_skills/Skill.py
alexa_skills/__init__.py
alexa_skills/helpers/Constants.py
alexa_skills/helpers/Util.py
alexa_skills/helpers/__init__.py
alexa_skills/requests/AbstractRequestHandler.py
alexa_skills/requests/HandlerInput.py
alexa_skills/requests/RequestHandler.py
alexa_skills/requests/__init__.py
alexa_skills/responses/Card.py
alexa_skills/responses/Dialog.py
alexa_skills/responses/OutputSpeech.py
alexa_skills/responses/Reprompt.py
alexa_skills/responses/Response.py
alexa_skills/responses/ResponseConstructor.py
alexa_skills/responses/__init__.py
alexa_skills/session/SessionManager.py
alexa_skills/session/__init__.py
alexa_skills-0.0.4.dist-info/LICENSE
alexa_skills-0.0.4.dist-info/METADATA
alexa_skills-0.0.4.dist-info/WHEEL
alexa_skills-0.0.4.dist-info/top_level.txt
alexa_skills-0.0.4.dist-info/RECORD
