Metadata-Version: 2.1
Name: alexa-skills
Version: 0.0.4
Summary: A Python Alexa Skills Package.
Home-page: https://github.com/johnyob/alexa-skills
Author: Alistair O'Brien
Author-email: alistair@duneroot.co.uk
License: UNKNOWN
Platform: UNKNOWN
